CHANGES.md
LICENSE
MANIFEST.in
README.md
setup.py
ArachneServer.egg-info/PKG-INFO
ArachneServer.egg-info/SOURCES.txt
ArachneServer.egg-info/dependency_links.txt
ArachneServer.egg-info/requires.txt
ArachneServer.egg-info/top_level.txt
arachneserver/__init__.py
arachneserver/default_endpoints.py
arachneserver/default_settings.py
arachneserver/exceptions.py
arachneserver/extensions.py
arachneserver/flaskapp.py
arachneserver/scrapy_utils.py
arachneserver/spider_data.csv