Metadata-Version: 1.0
Name: ArachneServer
Version: 1.0.2
Summary: API for Scrapy spiders
Home-page: https://github.com/dmkitui/arachneserver
Author: dmkitui
Author-email: dmkitui@gmail.com
License: BSD
Platform: UNKNOWN
